{
    "aquiles": [{
            "name": "Sem nome 1",
            "players": [
                "572180311417552896"
            ],
            "aquiles": ["1071434741707980880"]
        },
        {
            "name": "Sem nome 6",
            "players": [
                "761386273444724776",
                "1020904268410134569",
                "769252028312322048",
                "752283631371943946",
                "902666266630848533",
                "788845137161617418"
            ],
            "aquiles": ["689922678135718013"]
        },
        {
            "name": "Família Fontenegro",
            "players": [
                "529825718100820021",
                "256447387097235476",
                "1083333547814817842"
            ],
            "aquiles": [
                "788215107817701406",
                "1118279703074185387"
            ]
        }, {
            "name": "Sem nome 2",
            "players": [
                "1073785387845156864",
                "630128806128123904"
            ],
            "aquiles": [
                "1031008409635536926"
            ]
        }, {
            "name": "Sem nome 3",
            "players": [
                "483678402281340944",
                "669624507622752293"
            ],
            "aquiles": [
                "863127403331846164"
            ]
        }, {
            "name": "Sem nome 4",
            "players": [
                "768599043831889940",
                "353947630042349569",
                "686931630702854248"
            ],
            "aquiles": [
                "698584691187646485"
            ]
        }, {
            "name": "Sem nome 5",
            "players": [
                "607753154108325908",
                "608509130247766016"
            ],
            "aquiles": []
        }, {
            "name": "Família Bright",
            "players": [
                "408011078136496139"
            ],
            "aquiles": [
                "614178232438227022"
            ]
        },
        {
            "name": "Família Fror",
            "players": [
                "448535914629693442",
                "653577745086939147",
                "555560663536369665"
            ],
            "aquiles": [
                "519252336351248384"
            ]
        }, {
            "name": "Sem nome 7",
            "players": [
                "385811630199406602",
                "453650263417290753",
                "416316931973578772"
            ],
            "aquiles": []
        }, {
            "name": "Sem nome 8",
            "players": [
                "452197196394135553"
            ],
            "aquiles": [
                "841794014927912960"
            ]
        }
    ]
}